{
  "spin_excitation_energy": "ε",
  "spin_interaction_energy": "K",
  "number_of_spin_sites": "Nₛ",
  "simulation_end_time": "end_time",
  "chain_initial_state": "vₜ₌₀",
  "left_oscillator_initial_state": "ρₜ₌₀",
  "spin_initial_state": "spinₜ₌₀",
  "simulation_time_step": "τ",
  "MP_maximum_bond_dimension": "χ",
  "MP_compression_error": "compr_err",
  "TS_expansion_order": "T-S order",
  "spin_damping_coefficient": "κ",
  "oscillator_space_dimension": "dₒ",
  "oscillator_spin_interaction_coefficient": "κ",
  "oscillator_damping_coefficient_left": "γₗ",
  "oscillator_damping_coefficient_right": "γᵣ",
  "oscillator_frequency": "ω",
  "temperature": "T",
  "spectral_density_prop_constant": "λ",
  "spectral_density_peak": "Ω",
  "spectral_density_half_width": "γ",
  "frequency_cutoff": "g",
  "PolyChaos_nquad": "Nquad",
  "number_of_oscillators_left": "Nₗ",
  "number_of_oscillators_right": "Nᵣ",
  "ohmic_decay_factor": "Ω",
  "ohmic_exponent": "s",
  "ohmic_mult_factor": "λₒₕₘ"
}
